streamlit_image_viewer/__init__.py
streamlit_image_viewer/ImageViewer/__init__.py
streamlit_image_viewer/ImageViewer/app.py
streamlit_image_viewer/ImageViewer/frontend/build/asset-manifest.json
streamlit_image_viewer/ImageViewer/frontend/build/bootstrap.min.css
streamlit_image_viewer/ImageViewer/frontend/build/index.html
streamlit_image_viewer/ImageViewer/frontend/build/static/js/main.e8951d81.js
streamlit_image_viewer/ImageViewer/frontend/build/static/js/main.e8951d81.js.LICENSE.txt
streamlit_image_viewer/ImageViewer/frontend/build/static/js/main.e8951d81.js.map
streamlit_image_viewer-0.2.5.dist-info/LICENSE
streamlit_image_viewer-0.2.5.dist-info/METADATA
streamlit_image_viewer-0.2.5.dist-info/WHEEL
streamlit_image_viewer-0.2.5.dist-info/top_level.txt
streamlit_image_viewer-0.2.5.dist-info/RECORD
