Metadata-Version: 2.1
Name: streamlit-image-viewer
Version: 0.2.5
Summary: streamlit components for image viewer
Home-page: https://github.com/TakedaKatsuji/Streamlit-ImageViewer
Author: katsuji takeda
Keywords: Python,Streamlit,React,TypeScript
Requires-Python: >=3.9
License-File: LICENSE
Requires-Dist: streamlit (>=0.63)
